moat/kv/gpio/__init__.py
moat/kv/gpio/_cfg.yaml
moat/kv/gpio/_main.py
moat/kv/gpio/model.py
moat/kv/gpio/task.py
moat_kv_gpio-0.12.8.dist-info/licenses/LICENSE.txt
moat_kv_gpio-0.12.8.dist-info/METADATA
moat_kv_gpio-0.12.8.dist-info/WHEEL
moat_kv_gpio-0.12.8.dist-info/top_level.txt
moat_kv_gpio-0.12.8.dist-info/RECORD
