Metadata-Version: 2.4
Name: moat-kv-gpio
Version: 0.12.8
Summary: 1wire connector for MoaT-KV
Author-email: Matthias Urlichs <matthias@urlichs.de>
Project-URL: homepage, https://m-o-a-t.org
Project-URL: repository, https://github.com/M-o-a-T/moat
Keywords: MoaT
Classifier: Development Status :: 4 - Beta
Classifier: Intended Audience :: Information Technology
Classifier: Programming Language :: Python :: 3
Classifier: Topic :: Database
Classifier: Topic :: Home Automation
Requires-Python: >=3.8
License-File: LICENSE.txt
Requires-Dist: moat-kv~=0.71.20
Requires-Dist: moat-lib-gpio~=0.9.2
Requires-Dist: moat-lib-config~=0.1.0
Requires-Dist: moat-lib-run~=0.1.0
Requires-Dist: moat-util~=0.61.1
Dynamic: license-file
